{
  "model_name": "yolov10n_cv186x.bmodel",
        "image_num": 4,
        "results": {
            "computer.jpg":[
              {
                "bbox": [
                  75.326454,
                  42.405041,
                  349.996155,
                  252.030945
                ],
                "category_id": 63,
                "score": 0.947956
              }
            ],
            "plane.jpg": [
                {
                  "bbox": [
                    26.822388,
                    29.136215,
                    630.029419,
                    355.839661            
                  ],
                  "category_id": 4,
                  "score": 0.958674
                } 
            ],
            "san.jpg":[
              {
                "bbox":[
                  40.775169,
                  12.862371,
                  260.499054,
                  197.387024
                ],
                "category_id":25,
                "score":0.500000
              }
            ],
            "sofa.jpg":[
              {
                "bbox":[
                  51.124916,
                  84.892921,
                  360.647095,
                  218.644867
                ],
                "category_id":57,
                "score":0.898134
              }
            ]
      }
}
